xia_flask_api/__init__.py
xia_flask_api/rest.cpython-310-darwin.so
xia_flask_api/token.cpython-310-darwin.so
xia_flask_api/tools.cpython-310-darwin.so
xia_flask_api-0.1.8.dist-info/LICENSE.txt
xia_flask_api-0.1.8.dist-info/METADATA
xia_flask_api-0.1.8.dist-info/WHEEL
xia_flask_api-0.1.8.dist-info/top_level.txt
xia_flask_api-0.1.8.dist-info/RECORD
