Metadata-Version: 2.1
Name: xia-flask-api
Version: 0.1.8
Summary: X-I-A Flask API
Home-page: https://develop.x-i-a.com/docs/xia-flask-api/0.1.8/index.html
Author: X-I-A
Author-email: admin@x-i-a.com
License: UNKNOWN
Platform: UNKNOWN
Requires-Python: >=3.9
License-File: LICENSE.txt
Requires-Dist: Flask
Requires-Dist: requests
Requires-Dist: PyJWT
Requires-Dist: xia-cache-firestore
Requires-Dist: xia-engine-firestore
Requires-Dist: xia-meta
Requires-Dist: xia-meta-auth
Requires-Dist: xia-meta-task
Requires-Dist: xia-authenticator
Requires-Dist: xia-mail-sender
